slocum_ad2cp/__init__.py
slocum_ad2cp/analysis.py
slocum_ad2cp/make_dataset.py
slocum_ad2cp-2.0.0.dist-info/licenses/LICENSE
slocum_ad2cp-2.0.0.dist-info/METADATA
slocum_ad2cp-2.0.0.dist-info/WHEEL
slocum_ad2cp-2.0.0.dist-info/top_level.txt
slocum_ad2cp-2.0.0.dist-info/RECORD
